HW1/3-ASU/barrel_shifter.v
module barrel_shifter(in, shift, out);
input  [7:0] in;
input  [2:0] shift;
output [7:0] out;

/*Write your code here*/
reg zero= 0;
wire  [7:0] x1;
wire  [7:0] x2;
/*wire  [7:0] x1;
wire  [7:0] x2;
reg zero= 0;
assign x1[7:1]=(in[7:1] & ~shift[0]) | (in[6:0] & shift[0]);
assign x1[0]=(in[0] & ~shift[0]);

assign x2[7:2]=(x1[7:2] & ~shift[1]) | (x1[5:0] & shift[1]);
assign x2[1:0]=(x1[1:0] & ~shift[1]) ;

assign out[7:4]=(x2[7:4] & ~shift[2]) | (x2[3:0] & shift[2]);
assign out[3:0]=(x2[3:0] & ~shift[2]) ;
*/
assign x1[7:0] = (shift[0]==1'b1) ?   {in[6:0],zero}: in[7:0];
assign x2[7:0] =(shift[1]==1'b1) ?   {x1[5:0],zero,zero} : x1[7:0];
assign out[7:0] =(shift[2]==1'b1) ?   {x2[3:0],zero,zero,zero,zero} : x2[7:0];
/*End of code*/
endmodule

HW1/1-CR_Adder/adder_gate.v
module adder_gate(x, y, carry, out);
input [7:0] x, y;
output carry;
output [7:0] out;


/*Write your code here*/
    wire c1,c2,c3,c4,c5,c6,c7,c8;
    reg cin= 0;
    full_adder fa1(x[0],y[0],cin,out[0],c1);
    full_adder fa2(x[1],y[1],c1,out[1],c2);
    full_adder fa3(x[2],y[2],c2,out[2],c3);
    full_adder fa4(x[3],y[3],c3,out[3],c4);
    full_adder fa5(x[4],y[4],c4,out[4],c5);
    full_adder fa6(x[5],y[5],c5,out[5],c6);
    full_adder fa7(x[6],y[6],c6,out[6],c7);
    full_adder fa8(x[7],y[7],c7,out[7],carry);


/*End of code*/

endmodule

module full_adder(x1,y1,ci,sum,co);
    input x1, y1, ci;
    output co,sum;
    wire xy,yc,cx;

    and #1 g0(xy, x1, y1);
    and #1 g1(yc, y1, ci);
    and #1 g2(cx, x1, ci);
    or #1 g3(co, xy, yc, cx);
    xor #1 g4(sum, x1,y1, ci);

endmodule

HW1/3-ASU/asu.v
module asu (x, y, mode, carry, out);
input [7:0] x, y;
input mode;
output carry;
output [7:0] out;

/*Write your code here*/
reg [7:0] adder;
reg [7:0] shifter;
reg carry1;

adder_gate adder_1(x, y, carry1, adder);
barrel_shifter shifter_1(x, y[2:0], shifter);
assign out[7:0] = (mode==1'b1) ?   adder[7:0]: shifter[7:0];
assign carry = (mode==1'b1) ? carry1 : 1'b0;


/*End of code*/


endmodule

HW1/3-ASU/asu_test.v
`timescale 1ns/10ps
`define CYCLE 9
`define SELFILE "Msel.pattern"
`define INFILE "Min.pattern"
`define OUTFILE "Mout_golden.pattern" 

module asu_test;
parameter pattern_num = 10;
wire [7:0] out;
wire carry;
reg [7:0] x, y;
reg mode;
reg  clk;
reg  stop;
integer i, num, error;

reg [8:0] ans_out;
reg [8:0] mux_out;

reg [1:0] data_base0 [0:100];
reg [7:0] data_base1 [0:100];
reg [8:0] data_base2 [0:100];

asu t (x, y, mode, carry, out);

initial begin
	$readmemh(`SELFILE  , data_base0);
	$readmemh(`INFILE  , data_base1);
	$readmemh(`OUTFILE , data_base2);
	clk = 1'b1;
	error = 0;
	stop = 0;
	i=0;
end

always begin #(`CYCLE * 0.5) clk = ~clk;
end

initial begin
	mode = data_base0[0];
	x[7:0] = data_base1[0];
	y[7:0] = data_base1[1];
	
	for(num = 2; num < (pattern_num * 2); num = num + 2) begin
		@(posedge clk) begin
			mode = data_base0[num / 2];
			x[7:0] = data_base1[num];
			y[7:0] = data_base1[num + 1];
		end
	end
end


always@(posedge clk) begin
	i <= i + 1;
	if (i >= pattern_num)
		stop <= 1;
end

always@(posedge clk ) begin
	mux_out <= {carry, out};
	ans_out <= data_base2[i];
	if(mux_out !== ans_out) begin
		error <= error + 1;
		$display("An ERROR occurs at no.%d pattern: Output %b != answer %b.\n", i, mux_out, ans_out);
	end
end

initial begin
	@(posedge stop) begin
		if(error == 0) begin
			$display("==========================================\n");
			$display("======  Congratulation! You Pass!  =======\n");
			$display("==========================================\n");
		end
		else begin
			$display("===============================\n");
			$display("There are %d errors.", error);
			$display("===============================\n");
		end
		$finish;
	end
end

/*================Dumping Waveform files====================*/
initial begin
$dumpfile("mux.vcd");
$dumpvars;
/* 	$fsdbDumpfile("mux.fsdb");
	$fsdbDumpvars;  */
end

endmodule

HW1/3-ASU/mux.vcd
$date
    Mar 19, 2018  14:30:15
$end
$version
    TOOL:	ncsim	10.20-s114
$end
$timescale
    10 ps
$end

$scope module asu_test $end
$var parameter 32 !    pattern_num  $end
$var wire      8 "    out [7:0] $end
$var wire      1 #    carry  $end
$var reg       8 $    x [7:0] $end
$var reg       8 %    y [7:0] $end
$var reg       1 &    mode  $end
$var reg       1 '    clk  $end
$var reg       1 (    stop  $end
$var integer  32 )    i  $end
$var integer  32 *    num  $end
$var integer  32 +    error  $end
$var reg       9 ,    ans_out [8:0] $end
$var reg       9 -    mux_out [8:0] $end

$scope module t $end
$var wire      8 .    x [7:0] $end
$var wire      1 /    y [7] $end
$var wire      1 0    y [6] $end
$var wire      1 1    y [5] $end
$var wire      1 2    y [4] $end
$var wire      1 3    y [3] $end
$var wire      1 4    y [2] $end
$var wire      1 5    y [1] $end
$var wire      1 6    y [0] $end
$var wire      1 7    mode  $end
$var wire      1 #    carry  $end
$var wire      8 "    out [7:0] $end
$var wire      8 8    adder [7:0] $end
$var wire      8 9    shifter [7:0] $end
$var wire      1 :    carry1  $end

$scope module adder_1 $end
$var wire      8 .    x [7:0] $end
$var wire      1 /    y [7] $end
$var wire      1 0    y [6] $end
$var wire      1 1    y [5] $end
$var wire      1 2    y [4] $end
$var wire      1 3    y [3] $end
$var wire      1 4    y [2] $end
$var wire      1 5    y [1] $end
$var wire      1 6    y [0] $end
$var wire      1 :    carry  $end
$var wire      8 8    out [7:0] $end
$upscope $end


$scope module shifter_1 $end
$var wire      8 .    in [7:0] $end
$var wire      1 4    shift [2] $end
$var wire      1 5    shift [1] $end
$var wire      1 6    shift [0] $end
$var wire      8 9    out [7:0] $end
$var reg       1 ;    zero  $end
$var wire      8 <    x1 [7:0] $end
$var wire      8 =    x2 [7:0] $end
$upscope $end

$upscope $end

$upscope $end

$enddefinitions $end
$dumpvars
b1010 !
b10101010 "
0#
b10101010 $
b0 %
0&
1'
0(
b0 )
b10 *
b0 +
bx ,
bx -
b10101010 .
0/
00
01
02
03
04
05
06
07
b10101010 8
b10101010 9
0:
0;
b10101010 <
b10101010 =
$end
#1000
0'
#2000
1'
b1 %
b100 *
16
b10101011 8
b1010100 <
b1010100 =
b1010100 9
b1010100 "
b1 )
b10101010 -
b10101010 ,
#3000
0'
#4000
1'
b10 %
b110 *
15
06
b10101010 <
b10101100 8
b1010000 =
b1010000 9
b10101000 =
b10101000 9
b1010000 "
b10101000 "
b10 )
b1010100 -
b1010100 ,
#5000
0'
#6000
1'
b11 %
b1000 *
16
b10101101 8
b1010100 <
b1010000 =
b1010000 9
b1010000 "
b11 )
b10101000 -
b10101000 ,
#7000
0'
#8000
1'
1&
b1110000 $
b1111 %
b1010 *
13
14
b1110000 .
17
b10101101 "
b11100000 <
b0 9
b1111111 8
b1111111 "
b10000000 =
b100 )
b1010000 -
b1010000 ,
#9000
0'
#10000
1'
b11001001 $
b11110 %
b1100 *
12
06
b11001001 .
b11001001 <
b11100111 8
b11100111 "
b100100 =
b1000000 9
b101 )
b1111111 -
b1111111 ,
#11000
0'
#12000
1'
b1011011 $
b1101010 %
b1110 *
10
11
02
04
b1011011 .
b1011011 <
b100100 9
b11000101 8
b11000101 "
b1101100 =
b1101100 9
b110 )
b11100111 -
b11100111 ,
#13000
0'
#14000
1'
b11101 $
b11010001 %
b10000 *
1/
01
12
03
05
16
b11101 .
b111010 <
b1011011 =
b11101110 8
b11101110 "
b1011011 9
b111010 =
b111010 9
b111 )
b11000101 -
b11000101 ,
#15000
0'
#16000
1'
b11101001 $
b11111000 %
b10010 *
11
13
06
b11101001 .
b11101001 <
1:
b11100001 8
1#
b11100001 "
b11101001 =
b11101001 9
b1000 )
b11101110 -
b11101110 ,
#17000
0'
#18000
1'
b11110000 $
b11011 %
b10100 *
0/
00
01
15
16
b11110000 .
b11100000 <
b10100100 =
b1011 8
b1011 "
b10100100 9
b10000000 =
b10000000 9
b1001 )
b111100001 -
b111100001 ,
#19000
0'
#20000
1'
b1010 )
b100001011 -
b100001011 ,
#21000
0'
#22000
1'
b1011 )
1(
bx ,
